tilapya/__init__.py
tilapya/__version__.py
tilapya/_util.py
tilapya/errors.py
tilapya/gtfsrt.py
tilapya/rtds.py
tilapya/rtti.py
tilapya-1.0.0.dist-info/LICENSE
tilapya-1.0.0.dist-info/METADATA
tilapya-1.0.0.dist-info/WHEEL
tilapya-1.0.0.dist-info/top_level.txt
tilapya-1.0.0.dist-info/RECORD
