Metadata-Version: 2.1
Name: tilapya
Version: 1.0.0
Summary: TransLink Open API, in Python.
Home-page: https://github.com/carsonyl/tilapya
Author: Carson Lam
Author-email: carson.lam@alumni.ubc.ca
License: Apache Software License 2.0
Keywords: tilapya vancouver transit translink
Platform: UNKNOWN
Classifier: Development Status :: 2 - Pre-Alpha
Classifier: Intended Audience :: Developers
Classifier: License :: OSI Approved :: Apache Software License
Classifier: Natural Language :: English
Classifier: Programming Language :: Python :: 3
Classifier: Programming Language :: Python :: 3.5
Classifier: Programming Language :: Python :: 3.6
Classifier: Programming Language :: Python :: 3.7
Classifier: Topic :: Internet :: WWW/HTTP
Requires-Python: >=2.7,!=3.0.*,!=3.1.*,!=3.2.*,!=3.3.*
Requires-Dist: requests (<3.0.0,>=2.20.0)
Requires-Dist: marshmallow (<4.0.0,>=3.0.0rc7)
Requires-Dist: pytz
